CHANGELOG.rst
MANIFEST.in
README.rst
setup.py
slapos/__init__.py
slapos/crypto.py
slapos/libnetworkcache.py
slapos/libnetworkcachetests.py
slapos/separatedssltestserver.py
slapos/signature.py
slapos.libnetworkcache.egg-info/PKG-INFO
slapos.libnetworkcache.egg-info/SOURCES.txt
slapos.libnetworkcache.egg-info/dependency_links.txt
slapos.libnetworkcache.egg-info/entry_points.txt
slapos.libnetworkcache.egg-info/namespace_packages.txt
slapos.libnetworkcache.egg-info/requires.txt
slapos.libnetworkcache.egg-info/top_level.txt
slapos.libnetworkcache.egg-info/zip-safe