Metadata-Version: 2.1
Name: slapos.libnetworkcache
Version: 0.27
Summary: libnetworkcache - Client for ShaCache and ShaDir HTTP Server
License: GPLv3
Keywords: slapos networkcache shadir shacache
Classifier: Development Status :: 4 - Beta
Classifier: License :: OSI Approved :: GNU General Public License (GPL)
Classifier: Programming Language :: Python :: 2.7
Classifier: Programming Language :: Python :: 3
Classifier: Programming Language :: Python :: 3.7
Classifier: Programming Language :: Python :: 3.8
Classifier: Programming Language :: Python :: 3.9
Classifier: Programming Language :: Python :: 3.10
Classifier: Programming Language :: Python :: 3.11
Classifier: Programming Language :: Python :: 3.12
Requires-Python: >=2.7
